setup.cfg
setup.py
smartcsv/__init__.py
smartcsv/exceptions.py
smartcsv/reader.py
smartcsv.egg-info/PKG-INFO
smartcsv.egg-info/SOURCES.txt
smartcsv.egg-info/dependency_links.txt
smartcsv.egg-info/not-zip-safe
smartcsv.egg-info/top_level.txt