Metadata-Version: 1.1
Name: smartcsv
Version: 0.1.5
Summary: CSVs are awesome, yet they're pretty dumb. Let's get them smarter!
Home-page: http://github.com/santiagobasulto/smartcsv
Author: Santiago Basulto
Author-email: santiago.basulto@gmail.com
License: MIT
Download-URL: https://github.com/santiagobasulto/smartcsv/tarball/0.1.5
Platform: UNKNOWN
